taskqtool/__init__.py
taskqtool/api.py
taskqtool/client.py
taskqtool/crud.py
taskqtool/database.py
taskqtool/models.py
taskqtool/schemas.py
taskqtool/server.py
taskqtool/tools.py
taskqtool/cli/__init__.py
taskqtool/cli/del.py
taskqtool/cli/main.py
taskqtool/cli/serve.py
taskqtool/cli/show.py
taskqtool/cli/task.py
taskqtool/utils/__init__.py
taskqtool/utils/_common.py
taskqtool/utils/resources.py
taskqtool-0.0.28.dist-info/LICENSE
taskqtool-0.0.28.dist-info/METADATA
taskqtool-0.0.28.dist-info/WHEEL
taskqtool-0.0.28.dist-info/entry_points.txt
taskqtool-0.0.28.dist-info/top_level.txt
taskqtool-0.0.28.dist-info/RECORD
