Metadata-Version: 2.1
Name: taskqtool
Version: 0.0.28
Summary: Task queue tools
Home-page: http://zhcloud.top
Author: Hao Zhao
Author-email: 601095001@qq.com
License: OSI Approved :: MIT License
Platform: Linux/Windows
Classifier: Programming Language :: Python :: 3
Classifier: License :: OSI Approved :: MIT License
Classifier: Operating System :: OS Independent
Requires-Python: >=3.0
License-File: LICENSE
Requires-Dist: uvicorn (~=0.18.2)
Requires-Dist: fastapi (~=0.79.1)
Requires-Dist: setuptools (~=65.1.0)
Requires-Dist: service (~=0.6.0)
Requires-Dist: taskqtool (~=0.0.10)
Requires-Dist: requests (~=2.22.0)
Requires-Dist: pydantic (~=1.9.2)
Requires-Dist: SQLAlchemy (~=1.4.40)
Requires-Dist: starlette (~=0.19.1)
